perspectiveAnalyzer/PWRAP.py
perspectiveAnalyzer/__init__.py
perspectiveAnalyzer-1.0.2.dist-info/LICENSE
perspectiveAnalyzer-1.0.2.dist-info/METADATA
perspectiveAnalyzer-1.0.2.dist-info/WHEEL
perspectiveAnalyzer-1.0.2.dist-info/top_level.txt
perspectiveAnalyzer-1.0.2.dist-info/RECORD
