Metadata-Version: 2.1
Name: perspectiveAnalyzer
Version: 1.0.2
Summary: A simple python wrapper for perspective API
Home-page: https://github.com/dassaswat/perspectiveAnalyzer
Author: Saswat Das
Author-email: saswatd19@gmail.com
License: UNKNOWN
Keywords: python,api,discord,perspective api,text analyzer,google api client
Platform: UNKNOWN
Classifier: Development Status :: 3 - Alpha
Classifier: Intended Audience :: Developers
Classifier: License :: OSI Approved :: MIT License
Classifier: Programming Language :: Python :: 3
Classifier: Operating System :: Unix
Classifier: Operating System :: MacOS :: MacOS X
Classifier: Operating System :: Microsoft :: Windows
Requires-Dist: google-api-python-client (==2.6.0)
